thingking_machine/__init__.py
thingking_machine/githf.py
thingking_machine/machina.yaml
thingking_machine-0.0.3.dist-info/LICENSE
thingking_machine-0.0.3.dist-info/METADATA
thingking_machine-0.0.3.dist-info/WHEEL
thingking_machine-0.0.3.dist-info/top_level.txt
thingking_machine-0.0.3.dist-info/RECORD
